<?xml version="1.0"?>

<model-hints>
	<model name="com.kuongbk.model.Author">
		<field name="uuid" type="String" />
		<field name="authorId" type="long" />
		<field name="groupId" type="long" />
		<field name="companyId" type="long" />
		<field name="userId" type="long" />
		<field name="userName" type="String" />
		<field name="createDate" type="Date" />
		<field name="modifiedDate" type="Date" />
		<field name="name" type="String" />
		<field name="description" type="String" />
		<field name="born" type="Date" />
		<field name="male" type="Boolean" />
		<field name="status" type="int" />
	</model>
	<model name="com.kuongbk.model.Book">
		<field name="uuid" type="String" />
		<field name="bookId" type="long" />
		<field name="groupId" type="long" />
		<field name="companyId" type="long" />
		<field name="userId" type="long" />
		<field name="userName" type="String" />
		<field name="createDate" type="Date" />
		<field name="modifiedDate" type="Date" />
		<field name="name" type="String" />
		<field name="description" type="String" />
		<field name="publishDate" type="Date">
			<hint name="show-time">false</hint>
		</field>
		<field name="status" type="int" />
		<field name="viewCount" type="int" />
	</model>
</model-hints>